Workbook

Sheet Dashboard
A1: GLOBAL EMPLOYEE SHARE PLAN | OPERATIONS DASHBOARD
A3: Portfolio simulation • 2025–2026 • Data validation, reconciliation & compliance operations
A5: Employees Covered | D5: Transactions | G5: Gross Transaction Value | J5: Exceptions
A6: =COUNTA(Employee_Data!A2:A2001) | D6: =COUNTA(Share_Transactions!A2:A6001) | G6: =SUM(Share_Transactions!J2:J6001) | J6: =COUNTIF(Validation_Checks!N2:N6001,"INVESTIGATE")
A8: Operational view
A10: Exception Category | B10: Count | D10: Country | E10: Transactions | G10: Month | H10: Transaction Value
A11: Invalid Employee ID | B11: =COUNTIF(Validation_Checks!K2:K6001,"Invalid Employee") | D11: UK | E11: =COUNTIF(Share_Transactions!G2:G6001,D11) | G11: 45658 | H11: =SUMIFS(Share_Transactions!J:J,Share_Transactions!D:D,">="&G11,Share_Transactions!D:D,"<"&EDATE(G11,1))
A12: Invalid Share Quantity | B12: =COUNTIF(Validation_Checks!L2:L6001,"Invalid Shares") | D12: India | E12: =COUNTIF(Share_Transactions!G2:G6001,D12) | G12: 45689 | H12: =SUMIFS(Share_Transactions!J:J,Share_Transactions!D:D,">="&G12,Share_Transactions!D:D,"<"&EDATE(G12,1))
A13: Missing/Zero Tax | B13: =COUNTIF(Validation_Checks!M2:M6001,"Missing/Zero Tax") | D13: USA | E13: =COUNTIF(Share_Transactions!G2:G6001,D13) | G13: 45717 | H13: =SUMIFS(Share_Transactions!J:J,Share_Transactions!D:D,">="&G13,Share_Transactions!D:D,"<"&EDATE(G13,1))
A14: Approval Review | B14: =COUNTIF(Validation_Checks!O2:O6001,"Review Required") | D14: Singapore | E14: =COUNTIF(Share_Transactions!G2:G6001,D14) | G14: 45748 | H14: =SUMIFS(Share_Transactions!J:J,Share_Transactions!D:D,">="&G14,Share_Transactions!D:D,"<"&EDATE(G14,1))
D15: Australia | E15: =COUNTIF(Share_Transactions!G2:G6001,D15) | G15: 45778 | H15: =SUMIFS(Share_Transactions!J:J,Share_Transactions!D:D,">="&G15,Share_Transactions!D:D,"<"&EDATE(G15,1))
D16: Germany | E16: =COUNTIF(Share_Transactions!G2:G6001,D16) | G16: 45809 | H16: =SUMIFS(Share_Transactions!J:J,Share_Transactions!D:D,">="&G16,Share_Transactions!D:D,"<"&EDATE(G16,1))
G17: 45839 | H17: =SUMIFS(Share_Transactions!J:J,Share_Transactions!D:D,">="&G17,Share_Transactions!D:D,"<"&EDATE(G17,1))
G18: 45870 | H18: =SUMIFS(Share_Transactions!J:J,Share_Transactions!D:D,">="&G18,Share_Transactions!D:D,"<"&EDATE(G18,1))
G19: 45901 | H19: =SUMIFS(Share_Transactions!J:J,Share_Transactions!D:D,">="&G19,Share_Transactions!D:D,"<"&EDATE(G19,1))
G20: 45931 | H20: =SUMIFS(Share_Transactions!J:J,Share_Transactions!D:D,">="&G20,Share_Transactions!D:D,"<"&EDATE(G20,1))
G21: 45962 | H21: =SUMIFS(Share_Transactions!J:J,Share_Transactions!D:D,">="&G21,Share_Transactions!D:D,"<"&EDATE(G21,1))
G22: 45992 | H22: =SUMIFS(Share_Transactions!J:J,Share_Transactions!D:D,">="&G22,Share_Transactions!D:D,"<"&EDATE(G22,1))
G23: 46023 | H23: =SUMIFS(Share_Transactions!J:J,Share_Transactions!D:D,">="&G23,Share_Transactions!D:D,"<"&EDATE(G23,1))
G24: 46054 | H24: =SUMIFS(Share_Transactions!J:J,Share_Transactions!D:D,">="&G24,Share_Transactions!D:D,"<"&EDATE(G24,1))
G25: 46082 | H25: =SUMIFS(Share_Transactions!J:J,Share_Transactions!D:D,">="&G25,Share_Transactions!D:D,"<"&EDATE(G25,1))
G26: 46113 | H26: =SUMIFS(Share_Transactions!J:J,Share_Transactions!D:D,">="&G26,Share_Transactions!D:D,"<"&EDATE(G26,1))
G27: 46143 | H27: =SUMIFS(Share_Transactions!J:J,Share_Transactions!D:D,">="&G27,Share_Transactions!D:D,"<"&EDATE(G27,1))
G28: 46174 | H28: =SUMIFS(Share_Transactions!J:J,Share_Transactions!D:D,">="&G28,Share_Transactions!D:D,"<"&EDATE(G28,1))
... G34: 46357 | H34: =SUMIFS(Share_Transactions!J:J,Share_Transactions!D:D,">="&G34,Share_Transactions!D:D,"<"&EDATE(G34,1))

Sheet Employee_Data
A1: Employee_ID | B1: Employee_Name | C1: Country | D1: Department | E1: Job_Level | F1: Plan_Type | G1: Employment_Status | H1: Join_Date | I1: Grant_Date | J1: Vesting_Date
A2: EMP10001 | B2: Employee 1 | C2: UK | D2: People | E2: L4 | F2: RSU | G2: Active | H2: 45140 | I2: 45278 | J2: 46373
A3: EMP10002 | B3: Employee 2 | C3: Singapore | D3: Risk | E3: L3 | F3: RSU | G3: Active | H3: 45483 | I3: 45624 | J3: 45989
A4: EMP10003 | B4: Employee 3 | C4: India | D4: People | E4: L4 | F4: RSU | G4: Active | H4: 45004 | I4: 45044 | J4: 45409
A5: EMP10004 | B5: Employee 4 | C5: Singapore | D5: Sales | E5: L3 | F5: RSU | G5: Active | H5: 46062 | I5: 46345 | J5: 46710
A6: EMP10005 | B6: Employee 5 | C6: Germany | D6: Technology | E6: L3 | F6: RSU | G6: Active | H6: 46102 | I6: 46267 | J6: 47362
A7: EMP10006 | B7: Employee 6 | C7: USA | D7: Legal | E7: L2 | F7: RSU | G7: Active | H7: 45647 | I7: 45877 | J7: 46607
A8: EMP10007 | B8: Employee 7 | C8: India | D8: Finance | E8: L3 | F8: ESPP | G8: Active | H8: 45015 | I8: 45303 | J8: 46033
A9: EMP10008 | B9: Employee 8 | C9: UK | D9: Sales | E9: L4 | F9: RSU | G9: Active | H9: 45376 | I9: 45593 | J9: 46323
A10: EMP10009 | B10: Employee 9 | C10: UK | D10: Sales | E10: L5 | F10: Stock Option | G10: Active | H10: 44931 | I10: 45093 | J10: 45458
A11: EMP10010 | B11: Employee 10 | C11: India | D11: Sales | E11: L2 | F11: Stock Option | G11: Active | H11: 45603 | I11: 45792 | J11: 46522
A12: EMP10011 | B12: Employee 11 | C12: USA | D12: Legal | E12: L4 | F12: RSU | G12: Active | H12: 45646 | I12: 45841 | J12: 46206
A13: EMP10012 | B13: Employee 12 | C13: Singapore | D13: Legal | E13: L3 | F13: ESPP | G13: Active | H13: 45678 | I13: 45844 | J13: 46574
... A2001: EMP12000 | B2001: Employee 2000 | C2001: USA | D2001: Risk | E2001: L2 | F2001: ESPP | G2001: Active | H2001: 45268 | I2001: 45304 | J2001: 46399

Sheet Share_Transactions
A1: Transaction_ID | B1: Employee_ID | C1: Transaction_Type | D1: Transaction_Date | E1: Shares | F1: Share_Price_GBP | G1: Country | H1: Plan_Type | I1: Gross_Value_GBP | J1: Tax_Rate | K1: Expected_Tax_GBP | L1: Approval_Status | M1: High_Value_Flag
A2: TX500001 | B2: EMP10264 | C2: Sale | D2: 46223 | E2: 712 | F2: 89.94 | G2: Singapore | H2: RSU | I2: 64037.28 | J2: 0.2 | K2: 12807.46 | L2: Pending Review | M2: Normal
A3: TX500002 | B3: EMP10287 | C3: Grant | D3: 45710 | E3: 1673 | F3: 73.32 | G3: Singapore | H3: RSU | I3: 122664.36 | J3: 0.4 | K3: 49065.74 | L3: Approved | M3: High Value
A4: TX500003 | B4: EMP10901 | C4: Vesting | D4: 45697 | E4: 1772 | F4: 71.84 | G4: Singapore | H4: RSU | I4: 127300.48 | J4: 0.2 | K4: 25460.1 | L4: Approved | M4: High Value
A5: TX500004 | B5: EMP10201 | C5: Vesting | D5: 45863 | E5: 594 | F5: 34.12 | G5: Singapore | H5: RSU | I5: 20267.28 | J5: 0.4 | K5: 8106.91 | L5: Approved | M5: Normal
A6: TX500005 | B6: EMP11549 | C6: Grant | D6: 45845 | E6: 1334 | F6: 86.14 | G6: UK | H6: RSU | I6: 114910.76 | J6: 0.3 | K6: 34473.23 | L6: Approved | M6: High Value
A7: TX500006 | B7: EMP11528 | C7: Sale | D7: 46210 | E7: 1714 | F7: 6.68 | G7: UK | H7: RSU | I7: 11449.52 | J7: 0.2 | K7: 2289.9 | L7: Approved | M7: Normal
A8: TX500007 | B8: EMP11089 | C8: Sale | D8: 46369 | E8: 2227 | F8: 91.74 | G8: USA | H8: Stock Option | I8: 204304.98 | J8: 0.4 | K8: 81721.99 | L8: Approved | M8: High Value
A9: TX500008 | B9: EMP11616 | C9: Vesting | D9: 46147 | E9: 878 | F9: 61.02 | G9: UK | H9: RSU | I9: 53575.56 | J9: 0.45 | K9: 24109 | L9: Pending Review | M9: Normal
A10: TX500009 | B10: EMP10094 | C10: Exercise | D10: 45680 | E10: 2471 | F10: 29.87 | G10: Australia | H10: Performance Share | I10: 73808.77 | J10: 0.2 | K10: 14761.75 | L10: Approved | M10: Normal
A11: TX500010 | B11: EMP10328 | C11: Cancellation | D11: 46006 | E11: 2109 | F11: 45.4 | G11: UK | H11: Performance Share | I11: 95748.6 | J11: 0.2 | K11: 19149.72 | L11: Approved | M11: Normal
A12: TX500011 | B12: EMP11218 | C12: Sale | D12: 46083 | E12: 236 | F12: 74.13 | G12: Australia | H12: Stock Option | I12: 17494.68 | J12: 0.2 | K12: 3498.94 | L12: Approved | M12: Normal
A13: TX500012 | B13: EMP11796 | C13: Vesting | D13: 45796 | E13: 1542 | F13: 89.09 | G13: USA | H13: ESPP | I13: 137376.78 | J13: 0.3 | K13: 41213.03 | L13: Approved | M13: High Value
... A6001: TX506000 | B6001: EMP11589 | C6001: Exercise | D6001: 45684 | E6001: 2303 | F6001: 55.17 | G6001: Singapore | H6001: Stock Option | I6001: 127056.51 | J6001: 0.2 | K6001: 25411.3 | L6001: Approved | M6001: High Value

Sheet Payroll_Data
A1: Transaction_ID | B1: Employee_ID | C1: Payroll_Tax_GBP
A2: TX503887 | B2: EMP11597 | C2: 7316.26
A3: TX502145 | B3: EMP11705 | C3: 3040.74
A4: TX500440 | B4: EMP11302 | C4: 11347.38
A5: TX501876 | B5: EMP10158 | C5: 15382.3
A6: TX503401 | B6: EMP10279 | C6: 1469.2
A7: TX504836 | B7: EMP10411 | C7: 26606.65
A8: TX503763 | B8: EMP11886 | C8: 23380.07
A9: TX504683 | B9: EMP10201 | C9: 40184.96
A10: TX500567 | B10: EMP10852 | C10: 41000.19
A11: TX501342 | B11: EMP11543 | C11: 22944.08
A12: TX503553 | B12: EMP10143 | C12: 7262.51
A13: TX501161 | B13: EMP11140 | C13: 5653.61
... A2336: TX502140 | B2336: EMP10589 | C2336: 37182.12

Sheet Validation_Checks
A1: Transaction_ID | B1: Employee_ID | C1: Transaction_Type | D1: Transaction_Date | E1: Shares | F1: Gross_Value_GBP | G1: Expected_Tax_GBP | H1: Approval_Status | I1: Country | J1: Plan_Type | K1: Employee_ID_Check | L1: Shares_Check | M1: Tax_Check | N1: Overall_Status | O1: Approval_Check
A2: =Share_Transactions!A2 | B2: =Share_Transactions!B2 | C2: =Share_Transactions!C2 | D2: =Share_Transactions!D2 | E2: =Share_Transactions!E2 | F2: =Share_Transactions!J2 | G2: =Share_Transactions!L2 | H2: =Share_Transactions!M2 | I2: =Share_Transactions!G2 | J2: =Share_Transactions!H2 | K2: =IF(COUNTIF(Employee_Data!$A$2:$A$2001,B2)>0,"Valid","Invalid Employee") | L2: =IF(E2>0,"Valid","Invalid Shares") | M2: =IF(G2>0,"Valid","Valid","Missing/Zero Tax") | N2: =IF(AND(K2="Valid",L2="Valid",M2="Valid",O2="Approved"),"PASS","INVESTIGATE") | O2: =IF(H2="Approved","Approved","Review Required")
A3: =Share_Transactions!A3 | B3: =Share_Transactions!B3 | C3: =Share_Transactions!C3 | D3: =Share_Transactions!D3 | E3: =Share_Transactions!E3 | F3: =Share_Transactions!J3 | G3: =Share_Transactions!L3 | H3: =Share_Transactions!M3 | I3: =Share_Transactions!G3 | J3: =Share_Transactions!H3 | K3: =IF(COUNTIF(Employee_Data!$A$2:$A$2001,B3)>0,"Valid","Invalid Employee") | L3: =IF(E3>0,"Valid","Invalid Shares") | M3: =IF(G3>0,"Valid","Valid","Missing/Zero Tax") | N3: =IF(AND(K3="Valid",L3="Valid",M3="Valid",O3="Approved"),"PASS","INVESTIGATE") | O3: =IF(H3="Approved","Approved","Review Required")
A4: =Share_Transactions!A4 | B4: =Share_Transactions!B4 | C4: =Share_Transactions!C4 | D4: =Share_Transactions!D4 | E4: =Share_Transactions!E4 | F4: =Share_Transactions!J4 | G4: =Share_Transactions!L4 | H4: =Share_Transactions!M4 | I4: =Share_Transactions!G4 | J4: =Share_Transactions!H4 | K4: =IF(COUNTIF(Employee_Data!$A$2:$A$2001,B4)>0,"Valid","Invalid Employee") | L4: =IF(E4>0,"Valid","Invalid Shares") | M4: =IF(G4>0,"Valid","Valid","Missing/Zero Tax") | N4: =IF(AND(K4="Valid",L4="Valid",M4="Valid",O4="Approved"),"PASS","INVESTIGATE") | O4: =IF(H4="Approved","Approved","Review Required")
A5: =Share_Transactions!A5 | B5: =Share_Transactions!B5 | C5: =Share_Transactions!C5 | D5: =Share_Transactions!D5 | E5: =Share_Transactions!E5 | F5: =Share_Transactions!J5 | G5: =Share_Transactions!L5 | H5: =Share_Transactions!M5 | I5: =Share_Transactions!G5 | J5: =Share_Transactions!H5 | K5: =IF(COUNTIF(Employee_Data!$A$2:$A$2001,B5)>0,"Valid","Invalid Employee") | L5: =IF(E5>0,"Valid","Invalid Shares") | M5: =IF(G5>0,"Valid","Valid","Missing/Zero Tax") | N5: =IF(AND(K5="Valid",L5="Valid",M5="Valid",O5="Approved"),"PASS","INVESTIGATE") | O5: =IF(H5="Approved","Approved","Review Required")
A6: =Share_Transactions!A6 | B6: =Share_Transactions!B6 | C6: =Share_Transactions!C6 | D6: =Share_Transactions!D6 | E6: =Share_Transactions!E6 | F6: =Share_Transactions!J6 | G6: =Share_Transactions!L6 | H6: =Share_Transactions!M6 | I6: =Share_Transactions!G6 | J6: =Share_Transactions!H6 | K6: =IF(COUNTIF(Employee_Data!$A$2:$A$2001,B6)>0,"Valid","Invalid Employee") | L6: =IF(E6>0,"Valid","Invalid Shares") | M6: =IF(G6>0,"Valid","Valid","Missing/Zero Tax") | N6: =IF(AND(K6="Valid",L6="Valid",M6="Valid",O6="Approved"),"PASS","INVESTIGATE") | O6: =IF(H6="Approved","Approved","Review Required")
A7: =Share_Transactions!A7 | B7: =Share_Transactions!B7 | C7: =Share_Transactions!C7 | D7: =Share_Transactions!D7 | E7: =Share_Transactions!E7 | F7: =Share_Transactions!J7 | G7: =Share_Transactions!L7 | H7: =Share_Transactions!M7 | I7: =Share_Transactions!G7 | J7: =Share_Transactions!H7 | K7: =IF(COUNTIF(Employee_Data!$A$2:$A$2001,B7)>0,"Valid","Invalid Employee") | L7: =IF(E7>0,"Valid","Invalid Shares") | M7: =IF(G7>0,"Valid","Valid","Missing/Zero Tax") | N7: =IF(AND(K7="Valid",L7="Valid",M7="Valid",O7="Approved"),"PASS","INVESTIGATE") | O7: =IF(H7="Approved","Approved","Review Required")
A8: =Share_Transactions!A8 | B8: =Share_Transactions!B8 | C8: =Share_Transactions!C8 | D8: =Share_Transactions!D8 | E8: =Share_Transactions!E8 | F8: =Share_Transactions!J8 | G8: =Share_Transactions!L8 | H8: =Share_Transactions!M8 | I8: =Share_Transactions!G8 | J8: =Share_Transactions!H8 | K8: =IF(COUNTIF(Employee_Data!$A$2:$A$2001,B8)>0,"Valid","Invalid Employee") | L8: =IF(E8>0,"Valid","Invalid Shares") | M8: =IF(G8>0,"Valid","Valid","Missing/Zero Tax") | N8: =IF(AND(K8="Valid",L8="Valid",M8="Valid",O8="Approved"),"PASS","INVESTIGATE") | O8: =IF(H8="Approved","Approved","Review Required")
A9: =Share_Transactions!A9 | B9: =Share_Transactions!B9 | C9: =Share_Transactions!C9 | D9: =Share_Transactions!D9 | E9: =Share_Transactions!E9 | F9: =Share_Transactions!J9 | G9: =Share_Transactions!L9 | H9: =Share_Transactions!M9 | I9: =Share_Transactions!G9 | J9: =Share_Transactions!H9 | K9: =IF(COUNTIF(Employee_Data!$A$2:$A$2001,B9)>0,"Valid","Invalid Employee") | L9: =IF(E9>0,"Valid","Invalid Shares") | M9: =IF(G9>0,"Valid","Valid","Missing/Zero Tax") | N9: =IF(AND(K9="Valid",L9="Valid",M9="Valid",O9="Approved"),"PASS","INVESTIGATE") | O9: =IF(H9="Approved","Approved","Review Required")
A10: =Share_Transactions!A10 | B10: =Share_Transactions!B10 | C10: =Share_Transactions!C10 | D10: =Share_Transactions!D10 | E10: =Share_Transactions!E10 | F10: =Share_Transactions!J10 | G10: =Share_Transactions!L10 | H10: =Share_Transactions!M10 | I10: =Share_Transactions!G10 | J10: =Share_Transactions!H10 | K10: =IF(COUNTIF(Employee_Data!$A$2:$A$2001,B10)>0,"Valid","Invalid Employee") | L10: =IF(E10>0,"Valid","Invalid Shares") | M10: =IF(G10>0,"Valid","Valid","Missing/Zero Tax") | N10: =IF(AND(K10="Valid",L10="Valid",M10="Valid",O10="Approved"),"PASS","INVESTIGATE") | O10: =IF(H10="Approved","Approved","Review Required")
A11: =Share_Transactions!A11 | B11: =Share_Transactions!B11 | C11: =Share_Transactions!C11 | D11: =Share_Transactions!D11 | E11: =Share_Transactions!E11 | F11: =Share_Transactions!J11 | G11: =Share_Transactions!L11 | H11: =Share_Transactions!M11 | I11: =Share_Transactions!G11 | J11: =Share_Transactions!H11 | K11: =IF(COUNTIF(Employee_Data!$A$2:$A$2001,B11)>0,"Valid","Invalid Employee") | L11: =IF(E11>0,"Valid","Invalid Shares") | M11: =IF(G11>0,"Valid","Valid","Missing/Zero Tax") | N11: =IF(AND(K11="Valid",L11="Valid",M11="Valid",O11="Approved"),"PASS","INVESTIGATE") | O11: =IF(H11="Approved","Approved","Review Required")
A12: =Share_Transactions!A12 | B12: =Share_Transactions!B12 | C12: =Share_Transactions!C12 | D12: =Share_Transactions!D12 | E12: =Share_Transactions!E12 | F12: =Share_Transactions!J12 | G12: =Share_Transactions!L12 | H12: =Share_Transactions!M12 | I12: =Share_Transactions!G12 | J12: =Share_Transactions!H12 | K12: =IF(COUNTIF(Employee_Data!$A$2:$A$2001,B12)>0,"Valid","Invalid Employee") | L12: =IF(E12>0,"Valid","Invalid Shares") | M12: =IF(G12>0,"Valid","Valid","Missing/Zero Tax") | N12: =IF(AND(K12="Valid",L12="Valid",M12="Valid",O12="Approved"),"PASS","INVESTIGATE") | O12: =IF(H12="Approved","Approved","Review Required")
A13: =Share_Transactions!A13 | B13: =Share_Transactions!B13 | C13: =Share_Transactions!C13 | D13: =Share_Transactions!D13 | E13: =Share_Transactions!E13 | F13: =Share_Transactions!J13 | G13: =Share_Transactions!L13 | H13: =Share_Transactions!M13 | I13: =Share_Transactions!G13 | J13: =Share_Transactions!H13 | K13: =IF(COUNTIF(Employee_Data!$A$2:$A$2001,B13)>0,"Valid","Invalid Employee") | L13: =IF(E13>0,"Valid","Invalid Shares") | M13: =IF(G13>0,"Valid","Valid","Missing/Zero Tax") | N13: =IF(AND(K13="Valid",L13="Valid",M13="Valid",O13="Approved"),"PASS","INVESTIGATE") | O13: =IF(H13="Approved","Approved","Review Required")
... A6001: =Share_Transactions!A6001 | B6001: =Share_Transactions!B6001 | C6001: =Share_Transactions!C6001 | D6001: =Share_Transactions!D6001 | E6001: =Share_Transactions!E6001 | F6001: =Share_Transactions!J6001 | G6001: =Share_Transactions!L6001 | H6001: =Share_Transactions!M6001 | I6001: =Share_Transactions!G6001 | J6001: =Share_Transactions!H6001 | K6001: =IF(COUNTIF(Employee_Data!$A$2:$A$2001,B6001)>0,"Valid","Invalid Employee") | L6001: =IF(E6001>0,"Valid","Invalid Shares") | M6001: =IF(G6001>0,"Valid","Valid","Missing/Zero Tax") | N6001: =IF(AND(K6001="Valid",L6001="Valid",M6001="Valid",O6001="Approved"),"PASS","INVESTIGATE") | O6001: =IF(H6001="Approved","Approved","Review Required")

Sheet Reconciliation
A1: Transaction_ID | B1: Employee_ID | C1: Transaction_Type | D1: Expected_Tax_GBP | E1: Payroll_Tax_GBP | F1: Variance_GBP | G1: Reconciliation_Status
A2: TX500001 | B2: =XLOOKUP(A2,Share_Transactions!$A:$A,Share_Transactions!$B:$B,"") | C2: =XLOOKUP(A2,Share_Transactions!$A:$A,Share_Transactions!$C:$C,"") | D2: =XLOOKUP(A2,Share_Transactions!$A:$A,Share_Transactions!$L:$L,0) | E2: =XLOOKUP(A2,Payroll_Data!$A:$A,Payroll_Data!$D:$D,"") | F2: =IF(E2="","",D2-E2) | G2: =IF(E2="","Missing Payroll Record",IF(ABS(F2)<=1,"MATCH","MISMATCH"))
A3: TX500006 | B3: =XLOOKUP(A3,Share_Transactions!$A:$A,Share_Transactions!$B:$B,"") | C3: =XLOOKUP(A3,Share_Transactions!$A:$A,Share_Transactions!$C:$C,"") | D3: =XLOOKUP(A3,Share_Transactions!$A:$A,Share_Transactions!$L:$L,0) | E3: =XLOOKUP(A3,Payroll_Data!$A:$A,Payroll_Data!$D:$D,"") | F3: =IF(E3="","",D3-E3) | G3: =IF(E3="","Missing Payroll Record",IF(ABS(F3)<=1,"MATCH","MISMATCH"))
A4: TX500007 | B4: =XLOOKUP(A4,Share_Transactions!$A:$A,Share_Transactions!$B:$B,"") | C4: =XLOOKUP(A4,Share_Transactions!$A:$A,Share_Transactions!$C:$C,"") | D4: =XLOOKUP(A4,Share_Transactions!$A:$A,Share_Transactions!$L:$L,0) | E4: =XLOOKUP(A4,Payroll_Data!$A:$A,Payroll_Data!$D:$D,"") | F4: =IF(E4="","",D4-E4) | G4: =IF(E4="","Missing Payroll Record",IF(ABS(F4)<=1,"MATCH","MISMATCH"))
A5: TX500009 | B5: =XLOOKUP(A5,Share_Transactions!$A:$A,Share_Transactions!$B:$B,"") | C5: =XLOOKUP(A5,Share_Transactions!$A:$A,Share_Transactions!$C:$C,"") | D5: =XLOOKUP(A5,Share_Transactions!$A:$A,Share_Transactions!$L:$L,0) | E5: =XLOOKUP(A5,Payroll_Data!$A:$A,Payroll_Data!$D:$D,"") | F5: =IF(E5="","",D5-E5) | G5: =IF(E5="","Missing Payroll Record",IF(ABS(F5)<=1,"MATCH","MISMATCH"))
A6: TX500011 | B6: =XLOOKUP(A6,Share_Transactions!$A:$A,Share_Transactions!$B:$B,"") | C6: =XLOOKUP(A6,Share_Transactions!$A:$A,Share_Transactions!$C:$C,"") | D6: =XLOOKUP(A6,Share_Transactions!$A:$A,Share_Transactions!$L:$L,0) | E6: =XLOOKUP(A6,Payroll_Data!$A:$A,Payroll_Data!$D:$D,"") | F6: =IF(E6="","",D6-E6) | G6: =IF(E6="","Missing Payroll Record",IF(ABS(F6)<=1,"MATCH","MISMATCH"))
A7: TX500016 | B7: =XLOOKUP(A7,Share_Transactions!$A:$A,Share_Transactions!$B:$B,"") | C7: =XLOOKUP(A7,Share_Transactions!$A:$A,Share_Transactions!$C:$C,"") | D7: =XLOOKUP(A7,Share_Transactions!$A:$A,Share_Transactions!$L:$L,0) | E7: =XLOOKUP(A7,Payroll_Data!$A:$A,Payroll_Data!$D:$D,"") | F7: =IF(E7="","",D7-E7) | G7: =IF(E7="","Missing Payroll Record",IF(ABS(F7)<=1,"MATCH","MISMATCH"))
A8: TX500017 | B8: =XLOOKUP(A8,Share_Transactions!$A:$A,Share_Transactions!$B:$B,"") | C8: =XLOOKUP(A8,Share_Transactions!$A:$A,Share_Transactions!$C:$C,"") | D8: =XLOOKUP(A8,Share_Transactions!$A:$A,Share_Transactions!$L:$L,0) | E8: =XLOOKUP(A8,Payroll_Data!$A:$A,Payroll_Data!$D:$D,"") | F8: =IF(E8="","",D8-E8) | G8: =IF(E8="","Missing Payroll Record",IF(ABS(F8)<=1,"MATCH","MISMATCH"))
A9: TX500019 | B9: =XLOOKUP(A9,Share_Transactions!$A:$A,Share_Transactions!$B:$B,"") | C9: =XLOOKUP(A9,Share_Transactions!$A:$A,Share_Transactions!$C:$C,"") | D9: =XLOOKUP(A9,Share_Transactions!$A:$A,Share_Transactions!$L:$L,0) | E9: =XLOOKUP(A9,Payroll_Data!$A:$A,Payroll_Data!$D:$D,"") | F9: =IF(E9="","",D9-E9) | G9: =IF(E9="","Missing Payroll Record",IF(ABS(F9)<=1,"MATCH","MISMATCH"))
A10: TX500020 | B10: =XLOOKUP(A10,Share_Transactions!$A:$A,Share_Transactions!$B:$B,"") | C10: =XLOOKUP(A10,Share_Transactions!$A:$A,Share_Transactions!$C:$C,"") | D10: =XLOOKUP(A10,Share_Transactions!$A:$A,Share_Transactions!$L:$L,0) | E10: =XLOOKUP(A10,Payroll_Data!$A:$A,Payroll_Data!$D:$D,"") | F10: =IF(E10="","",D10-E10) | G10: =IF(E10="","Missing Payroll Record",IF(ABS(F10)<=1,"MATCH","MISMATCH"))
A11: TX500021 | B11: =XLOOKUP(A11,Share_Transactions!$A:$A,Share_Transactions!$B:$B,"") | C11: =XLOOKUP(A11,Share_Transactions!$A:$A,Share_Transactions!$C:$C,"") | D11: =XLOOKUP(A11,Share_Transactions!$A:$A,Share_Transactions!$L:$L,0) | E11: =XLOOKUP(A11,Payroll_Data!$A:$A,Payroll_Data!$D:$D,"") | F11: =IF(E11="","",D11-E11) | G11: =IF(E11="","Missing Payroll Record",IF(ABS(F11)<=1,"MATCH","MISMATCH"))
A12: TX500024 | B12: =XLOOKUP(A12,Share_Transactions!$A:$A,Share_Transactions!$B:$B,"") | C12: =XLOOKUP(A12,Share_Transactions!$A:$A,Share_Transactions!$C:$C,"") | D12: =XLOOKUP(A12,Share_Transactions!$A:$A,Share_Transactions!$L:$L,0) | E12: =XLOOKUP(A12,Payroll_Data!$A:$A,Payroll_Data!$D:$D,"") | F12: =IF(E12="","",D12-E12) | G12: =IF(E12="","Missing Payroll Record",IF(ABS(F12)<=1,"MATCH","MISMATCH"))
A13: TX500026 | B13: =XLOOKUP(A13,Share_Transactions!$A:$A,Share_Transactions!$B:$B,"") | C13: =XLOOKUP(A13,Share_Transactions!$A:$A,Share_Transactions!$C:$C,"") | D13: =XLOOKUP(A13,Share_Transactions!$A:$A,Share_Transactions!$L:$L,0) | E13: =XLOOKUP(A13,Payroll_Data!$A:$A,Payroll_Data!$D:$D,"") | F13: =IF(E13="","",D13-E13) | G13: =IF(E13="","Missing Payroll Record",IF(ABS(F13)<=1,"MATCH","MISMATCH"))
... A2595: TX506000 | B2595: =XLOOKUP(A2595,Share_Transactions!$A:$A,Share_Transactions!$B:$B,"") | C2595: =XLOOKUP(A2595,Share_Transactions!$A:$A,Share_Transactions!$C:$C,"") | D2595: =XLOOKUP(A2595,Share_Transactions!$A:$A,Share_Transactions!$L:$L,0) | E2595: =XLOOKUP(A2595,Payroll_Data!$A:$A,Payroll_Data!$D:$D,"") | F2595: =IF(E2595="","",D2595-E2595) | G2595: =IF(E2595="","Missing Payroll Record",IF(ABS(F2595)<=1,"MATCH","MISMATCH"))

Sheet Business_Insights
A1: BUSINESS INSIGHTS & INVESTIGATION GUIDE
A4: Purpose | B4: Use this sheet to translate data-quality results into operational actions.
A6: Investigation Area | B6: Business Interpretation | C6: Recommended Action
A7: Invalid employee IDs | B7: Transaction cannot be reliably linked to an employee master record. | C7: Validate source file and hold transaction until corrected.
A8: Invalid share quantities | B8: Negative or invalid quantities indicate a potential processing/data-entry issue. | C8: Check source transaction and confirm the intended share quantity.
A9: Missing/zero tax | B9: Tax value is absent where a deduction is expected. | C9: Review payroll/tax calculation before settlement.
A10: Approval review | B10: Transaction has not reached the simulated approval state. | C10: Route to the appropriate approver before processing.
A11: Payroll mismatch | B11: Share-plan tax differs materially from payroll record. | C11: Reconcile transaction, tax rate and payroll deduction.

Sheet Data_Dictionary
A1: Field | B1: Sheet | C1: Definition | D1: Type
A2: Employee_ID | B2: Employee_Data | C2: Unique employee identifier | D2: Key
A3: Country | B3: Employee_Data | C3: Employee's country of employment | D3: Dimension
A4: Plan_Type | B4: Employee_Data | C4: Employee share-plan type | D4: Dimension
A5: Transaction_ID | B5: Share_Transactions | C5: Unique transaction identifier | D5: Key
A6: Transaction_Type | B6: Share_Transactions | C6: Grant, vesting, exercise, sale or cancellation | D6: Dimension
A7: Shares | B7: Share_Transactions | C7: Number of shares involved | D7: Measure
A8: Gross_Value_GBP | B8: Share_Transactions | C8: Shares multiplied by share price | D8: Measure
A9: Expected_Tax_GBP | B9: Share_Transactions | C9: Simulated expected tax deduction | D9: Measure
A10: Approval_Status | B10: Share_Transactions | C10: Simulated operational approval status | D10: Control
A11: Payroll_Tax_GBP | B11: Payroll_Data | C11: Simulated payroll tax deduction | D11: Measure
A12: Reconciliation_Status | B12: Reconciliation | C12: Comparison of share-plan and payroll tax | D12: Control
